clidantic/__init__.py
clidantic/click.py
clidantic/convert.py
clidantic/core.py
clidantic/testing.py
clidantic/types.py
clidantic-0.1.0.dist-info/LICENSE
clidantic-0.1.0.dist-info/WHEEL
clidantic-0.1.0.dist-info/METADATA
clidantic-0.1.0.dist-info/RECORD
